[
  {
    "id": "v1",
    "title": "Play all",
    "description": "Watch Play all on YourSpace.",
    "content_type": "video",
    "file_url": "https://img.youtube.com/vi/CRUha9WxbxE/hqdefault.jpg",
    "view_count": 49066,
    "like_count": 4826,
    "created_at": "2025-11-25T22:33:57.719Z",
    "vibe_tags": [
      "futuristic",
      "energetic"
    ]
  },
  {
    "id": "v2",
    "title": "💥 {voidtv} Presents: Sofa King Sad Boi - Artistic Visual Delights! 🎨✨12matt3r",
    "description": "Watch 💥 {voidtv} Presents: Sofa King Sad Boi - Artistic Visual Delights! 🎨✨12matt3r on YourSpace.",
    "content_type": "video",
    "file_url": "https://img.youtube.com/vi/BkTZWDlbHug/hqdefault.jpg",
    "view_count": 9904,
    "like_count": 500,
    "created_at": "2025-12-02T00:05:07.755Z",
    "vibe_tags": [
      "chill",
      "energetic"
    ]
  },
  {
    "id": "v3",
    "title": "ＢＵＭＰ ＴＶ | EPISODE 6",
    "description": "Watch ＢＵＭＰ ＴＶ | EPISODE 6 on YourSpace.",
    "content_type": "video",
    "file_url": "https://img.youtube.com/vi/GOjr3p10wXo/hqdefault.jpg",
    "view_count": 46839,
    "like_count": 4378,
    "created_at": "2025-12-23T12:14:32.163Z",
    "vibe_tags": [
      "futuristic",
      "retro"
    ]
  },
  {
    "id": "v4",
    "title": "ＢＵＭＰ | EPISODE 5",
    "description": "Watch ＢＵＭＰ | EPISODE 5 on YourSpace.",
    "content_type": "video",
    "file_url": "https://img.youtube.com/vi/Ip2ajcVdmuI/hqdefault.jpg",
    "view_count": 41275,
    "like_count": 4503,
    "created_at": "2025-10-07T23:22:58.068Z",
    "vibe_tags": [
      "futuristic",
      "energetic"
    ]
  },
  {
    "id": "v5",
    "title": "ＢＵＭＰ| EPISODE 4",
    "description": "Watch ＢＵＭＰ| EPISODE 4 on YourSpace.",
    "content_type": "video",
    "file_url": "https://img.youtube.com/vi/-BofMq2_e_4/hqdefault.jpg",
    "view_count": 32400,
    "like_count": 2980,
    "created_at": "2025-12-23T20:10:26.355Z",
    "vibe_tags": [
      "chill",
      "energetic"
    ]
  },
  {
    "id": "v6",
    "title": "ＢＵＭＰ| EPISODE 3",
    "description": "Watch ＢＵＭＰ| EPISODE 3 on YourSpace.",
    "content_type": "video",
    "file_url": "https://img.youtube.com/vi/h-B77YzTUPQ/hqdefault.jpg",
    "view_count": 48675,
    "like_count": 1182,
    "created_at": "2025-09-21T08:19:51.389Z",
    "vibe_tags": [
      "retro",
      "energetic"
    ]
  },
  {
    "id": "v7",
    "title": "ＢＵＭＰ| EPISODE 2",
    "description": "Watch ＢＵＭＰ| EPISODE 2 on YourSpace.",
    "content_type": "video",
    "file_url": "https://img.youtube.com/vi/w0U8nKw8uB0/hqdefault.jpg",
    "view_count": 4496,
    "like_count": 2930,
    "created_at": "2025-10-19T20:25:00.334Z",
    "vibe_tags": [
      "futuristic",
      "chill"
    ]
  },
  {
    "id": "v8",
    "title": "ＢＵＭＰ| EPISODE 1",
    "description": "Watch ＢＵＭＰ| EPISODE 1 on YourSpace.",
    "content_type": "video",
    "file_url": "https://img.youtube.com/vi/p1M0lKvEYzo/hqdefault.jpg",
    "view_count": 39877,
    "like_count": 4519,
    "created_at": "2025-12-05T11:03:37.569Z",
    "vibe_tags": [
      "energetic",
      "chill"
    ]
  },
  {
    "id": "v9",
    "title": "Addicting Addictions - NoEmotion And The Godz- Prod by class",
    "description": "Watch Addicting Addictions - NoEmotion And The Godz- Prod by class on YourSpace.",
    "content_type": "video",
    "file_url": "https://img.youtube.com/vi/6vo0Tsz8R-g/hqdefault.jpg",
    "view_count": 5595,
    "like_count": 154,
    "created_at": "2025-11-06T23:42:25.429Z",
    "vibe_tags": [
      "futuristic",
      "retro"
    ]
  },
  {
    "id": "v10",
    "title": "Fiercely Fisting - NoEmotion and The Godz - Prod by @mastakonkurer",
    "description": "Watch Fiercely Fisting - NoEmotion and The Godz - Prod by @mastakonkurer on YourSpace.",
    "content_type": "video",
    "file_url": "https://img.youtube.com/vi/uWzR-YizSE0/hqdefault.jpg",
    "view_count": 48773,
    "like_count": 370,
    "created_at": "2025-11-08T15:20:54.584Z",
    "vibe_tags": [
      "retro",
      "energetic"
    ]
  },
  {
    "id": "v11",
    "title": "MIXTAPE #1000 - THE CYBER TAPE (Cyberpunk Glitch Art ||| 2024)",
    "description": "Watch MIXTAPE #1000 - THE CYBER TAPE (Cyberpunk Glitch Art ||| 2024) on YourSpace.",
    "content_type": "video",
    "file_url": "https://img.youtube.com/vi/A9FyxnTvtHU/hqdefault.jpg",
    "view_count": 15311,
    "like_count": 4350,
    "created_at": "2025-10-22T20:03:01.120Z",
    "vibe_tags": [
      "futuristic",
      "retro"
    ]
  },
  {
    "id": "v12",
    "title": "Juice WRLD - Already Dead - Eastland Phuks - Official Music Video Remix Visualizer - Lyrical Lemon",
    "description": "Watch Juice WRLD - Already Dead - Eastland Phuks - Official Music Video Remix Visualizer - Lyrical Lemon on YourSpace.",
    "content_type": "video",
    "file_url": "https://img.youtube.com/vi/TZyXIc1wUyE/hqdefault.jpg",
    "view_count": 15134,
    "like_count": 659,
    "created_at": "2025-10-22T10:03:57.446Z",
    "vibe_tags": [
      "retro",
      "futuristic"
    ]
  },
  {
    "id": "v13",
    "title": "Sofa King Sad boi: An Audio/Visual Stimulants Mixtape",
    "description": "Watch Sofa King Sad boi: An Audio/Visual Stimulants Mixtape on YourSpace.",
    "content_type": "video",
    "file_url": "https://img.youtube.com/vi/PQl6m0iDQGs/hqdefault.jpg",
    "view_count": 40952,
    "like_count": 2967,
    "created_at": "2025-10-27T06:17:26.470Z",
    "vibe_tags": [
      "retro",
      "futuristic"
    ]
  },
  {
    "id": "v14",
    "title": "Visual Stimulants :: Off the Air :: Trip to this :: Audio/Video Mixtape #Adult Swim :: Deluxe",
    "description": "Watch Visual Stimulants :: Off the Air :: Trip to this :: Audio/Video Mixtape #Adult Swim :: Deluxe on YourSpace.",
    "content_type": "video",
    "file_url": "https://img.youtube.com/vi/TjDuNXk4-DM/hqdefault.jpg",
    "view_count": 42862,
    "like_count": 3937,
    "created_at": "2025-12-20T07:15:14.122Z",
    "vibe_tags": [
      "futuristic",
      "retro"
    ]
  },
  {
    "id": "v15",
    "title": "Best Vaporwave Mix of Memories that never happened! Or Did They?",
    "description": "Watch Best Vaporwave Mix of Memories that never happened! Or Did They? on YourSpace.",
    "content_type": "video",
    "file_url": "https://img.youtube.com/vi/nxga-0hJYgA/hqdefault.jpg",
    "view_count": 23384,
    "like_count": 2001,
    "created_at": "2025-10-13T15:52:15.063Z",
    "vibe_tags": [
      "futuristic",
      "retro"
    ]
  },
  {
    "id": "v16",
    "title": "RELIVE The Most insane, Bassnectar tribute original audio | visual experience in the world",
    "description": "Watch RELIVE The Most insane, Bassnectar tribute original audio | visual experience in the world on YourSpace.",
    "content_type": "video",
    "file_url": "https://img.youtube.com/vi/fDeF5lk24OU/hqdefault.jpg",
    "view_count": 33923,
    "like_count": 3481,
    "created_at": "2025-10-15T09:06:16.976Z",
    "vibe_tags": [
      "futuristic",
      "retro"
    ]
  },
  {
    "id": "v17",
    "title": "Bent // Broken Circuit Bending Festival 2024 ( 12matt3r )",
    "description": "Watch Bent // Broken Circuit Bending Festival 2024 ( 12matt3r ) on YourSpace.",
    "content_type": "video",
    "file_url": "https://img.youtube.com/vi/YwwefX7-0r0/hqdefault.jpg",
    "view_count": 3023,
    "like_count": 1798,
    "created_at": "2025-11-11T20:04:44.653Z",
    "vibe_tags": [
      "chill",
      "futuristic"
    ]
  },
  {
    "id": "v18",
    "title": "Glitch Guild Cybertape 12matt3r",
    "description": "Watch Glitch Guild Cybertape 12matt3r on YourSpace.",
    "content_type": "video",
    "file_url": "https://img.youtube.com/vi/R3buJ1dqZN4/hqdefault.jpg",
    "view_count": 48280,
    "like_count": 4849,
    "created_at": "2025-11-04T17:33:40.273Z",
    "vibe_tags": [
      "energetic",
      "futuristic"
    ]
  },
  {
    "id": "v19",
    "title": "The 8 Hour Reflection: A Noemotion Goldmask Odyssey | Full Documentary",
    "description": "Watch The 8 Hour Reflection: A Noemotion Goldmask Odyssey | Full Documentary on YourSpace.",
    "content_type": "video",
    "file_url": "https://img.youtube.com/vi/R_ud4QVM4fY/hqdefault.jpg",
    "view_count": 50416,
    "like_count": 4529,
    "created_at": "2026-01-04T16:02:47.144Z",
    "vibe_tags": [
      "retro",
      "energetic"
    ]
  },
  {
    "id": "v20",
    "title": "SSCC Volume 5: Brief Glimpses of Quicksilver Dreams; or, Slush in a Rush Visual Album",
    "description": "Watch SSCC Volume 5: Brief Glimpses of Quicksilver Dreams; or, Slush in a Rush Visual Album on YourSpace.",
    "content_type": "video",
    "file_url": "https://img.youtube.com/vi/MeW42PuTTk0/hqdefault.jpg",
    "view_count": 8583,
    "like_count": 2623,
    "created_at": "2025-09-26T05:59:40.001Z",
    "vibe_tags": [
      "retro",
      "energetic"
    ]
  },
  {
    "id": "v21",
    "title": "\"The Bizarre Ruby Bear Infomercial\" | 12matt3r Short Film |",
    "description": "Watch \"The Bizarre Ruby Bear Infomercial\" | 12matt3r Short Film | on YourSpace.",
    "content_type": "video",
    "file_url": "https://img.youtube.com/vi/mgMwjbqRWv8/hqdefault.jpg",
    "view_count": 5864,
    "like_count": 2739,
    "created_at": "2025-09-29T06:59:16.471Z",
    "vibe_tags": [
      "chill",
      "energetic"
    ]
  },
  {
    "id": "v22",
    "title": "Secret trippy World of Discarded Dreams Revealed Through chill Lo-Fi phonk",
    "description": "Watch Secret trippy World of Discarded Dreams Revealed Through chill Lo-Fi phonk on YourSpace.",
    "content_type": "video",
    "file_url": "https://img.youtube.com/vi/a7iHkZFwbrU/hqdefault.jpg",
    "view_count": 11640,
    "like_count": 2388,
    "created_at": "2025-12-16T16:54:03.308Z",
    "vibe_tags": [
      "retro",
      "energetic"
    ]
  },
  {
    "id": "v23",
    "title": "Space Jesus The WEED \"Nawledge\" 12MATT3R REMIX",
    "description": "Watch Space Jesus The WEED \"Nawledge\" 12MATT3R REMIX on YourSpace.",
    "content_type": "video",
    "file_url": "https://img.youtube.com/vi/3RlU_Q1PR44/hqdefault.jpg",
    "view_count": 1215,
    "like_count": 2863,
    "created_at": "2025-10-28T08:07:29.756Z",
    "vibe_tags": [
      "chill",
      "energetic"
    ]
  },
  {
    "id": "v24",
    "title": "listening party number 52.1439 through the gods canal of birth",
    "description": "Watch listening party number 52.1439 through the gods canal of birth on YourSpace.",
    "content_type": "video",
    "file_url": "https://img.youtube.com/vi/5_7FV5_N1so/hqdefault.jpg",
    "view_count": 10719,
    "like_count": 4554,
    "created_at": "2025-12-06T21:07:38.806Z",
    "vibe_tags": [
      "chill",
      "energetic"
    ]
  },
  {
    "id": "v25",
    "title": "Bassnectar -The Golden Rule: Full Album Vizualizer",
    "description": "Watch Bassnectar -The Golden Rule: Full Album Vizualizer on YourSpace.",
    "content_type": "video",
    "file_url": "https://img.youtube.com/vi/kmm6udgnjmM/hqdefault.jpg",
    "view_count": 10303,
    "like_count": 1924,
    "created_at": "2025-12-13T23:36:00.529Z",
    "vibe_tags": [
      "chill",
      "energetic"
    ]
  },
  {
    "id": "v26",
    "title": "12matt3r Unlocking the Imagination: A Psychedelic Journey into the Mind of a Child!",
    "description": "Watch 12matt3r Unlocking the Imagination: A Psychedelic Journey into the Mind of a Child! on YourSpace.",
    "content_type": "video",
    "file_url": "https://img.youtube.com/vi/Q7mJlTMUlkM/hqdefault.jpg",
    "view_count": 41006,
    "like_count": 4222,
    "created_at": "2025-12-17T13:17:41.119Z",
    "vibe_tags": [
      "chill",
      "energetic"
    ]
  },
  {
    "id": "v27",
    "title": "A Mind-Blowing Journey Through the Visual Stimulants of Bent // Broken 2023",
    "description": "Watch A Mind-Blowing Journey Through the Visual Stimulants of Bent // Broken 2023 on YourSpace.",
    "content_type": "video",
    "file_url": "https://img.youtube.com/vi/F335672e88I/hqdefault.jpg",
    "view_count": 34541,
    "like_count": 3832,
    "created_at": "2025-11-23T12:59:20.126Z",
    "vibe_tags": [
      "futuristic",
      "retro"
    ]
  },
  {
    "id": "v28",
    "title": "Space Jesus - SPACE JAM | Glitch Guild Space Tape | (sofa Sauce) | 12matt3r Visuals",
    "description": "Watch Space Jesus - SPACE JAM | Glitch Guild Space Tape | (sofa Sauce) | 12matt3r Visuals on YourSpace.",
    "content_type": "video",
    "file_url": "https://img.youtube.com/vi/aCyiGt6kxXA/hqdefault.jpg",
    "view_count": 7804,
    "like_count": 4089,
    "created_at": "2026-01-04T21:44:10.945Z",
    "vibe_tags": [
      "retro",
      "futuristic"
    ]
  },
  {
    "id": "v29",
    "title": "Slushwave Social Club Volume 6: Autumn Memories | Visual Album",
    "description": "Watch Slushwave Social Club Volume 6: Autumn Memories | Visual Album on YourSpace.",
    "content_type": "video",
    "file_url": "https://img.youtube.com/vi/6-X6J7ZP7Bc/hqdefault.jpg",
    "view_count": 20502,
    "like_count": 4435,
    "created_at": "2025-10-14T10:54:20.587Z",
    "vibe_tags": [
      "futuristic",
      "energetic"
    ]
  },
  {
    "id": "v30",
    "title": "NOCOUNTRY FOR GOLDMASK - tangerines and tambourines",
    "description": "Watch NOCOUNTRY FOR GOLDMASK - tangerines and tambourines on YourSpace.",
    "content_type": "video",
    "file_url": "https://img.youtube.com/vi/Qj723jcm3Rw/hqdefault.jpg",
    "view_count": 37355,
    "like_count": 1128,
    "created_at": "2025-10-27T01:06:03.765Z",
    "vibe_tags": [
      "chill",
      "futuristic"
    ]
  },
  {
    "id": "v31",
    "title": "Kanye Twitty - Wrestlemania",
    "description": "Watch Kanye Twitty - Wrestlemania on YourSpace.",
    "content_type": "video",
    "file_url": "https://img.youtube.com/vi/OxFG0gOFmUI/hqdefault.jpg",
    "view_count": 34694,
    "like_count": 4706,
    "created_at": "2025-10-30T22:37:56.669Z",
    "vibe_tags": [
      "chill",
      "energetic"
    ]
  },
  {
    "id": "v32",
    "title": "The 8 Hour Reflection: A Noemotion Goldmask Odyssey | ACT 1",
    "description": "Watch The 8 Hour Reflection: A Noemotion Goldmask Odyssey | ACT 1 on YourSpace.",
    "content_type": "video",
    "file_url": "https://img.youtube.com/vi/fuTHCtQGNZg/hqdefault.jpg",
    "view_count": 47981,
    "like_count": 1433,
    "created_at": "2025-10-08T04:23:56.599Z",
    "vibe_tags": [
      "chill",
      "energetic"
    ]
  },
  {
    "id": "v33",
    "title": "The Crawling Mind:Gen48 Surreal AI Short Film (Experimental Animation)",
    "description": "Watch The Crawling Mind:Gen48 Surreal AI Short Film (Experimental Animation) on YourSpace.",
    "content_type": "video",
    "file_url": "https://img.youtube.com/vi/Egqeo2_s-fw/hqdefault.jpg",
    "view_count": 31673,
    "like_count": 3662,
    "created_at": "2025-11-20T10:31:53.405Z",
    "vibe_tags": [
      "energetic",
      "futuristic"
    ]
  },
  {
    "id": "v34",
    "title": "Play all",
    "description": "Watch Play all on YourSpace.",
    "content_type": "video",
    "file_url": "https://img.youtube.com/vi/d2cTJS0XTEk/hqdefault.jpg",
    "view_count": 1609,
    "like_count": 4046,
    "created_at": "2025-12-20T23:27:07.908Z",
    "vibe_tags": [
      "energetic",
      "retro"
    ]
  },
  {
    "id": "v35",
    "title": "Visual Stimulants 12Matt3r",
    "description": "Watch Visual Stimulants 12Matt3r on YourSpace.",
    "content_type": "video",
    "file_url": "https://img.youtube.com/vi/i-ehCBD_z1Y/hqdefault.jpg",
    "view_count": 9204,
    "like_count": 3546,
    "created_at": "2026-01-11T12:25:54.791Z",
    "vibe_tags": [
      "futuristic",
      "retro"
    ]
  },
  {
    "id": "v36",
    "title": "SLUSHWAVE 2025 | Driftwave Static",
    "description": "Watch SLUSHWAVE 2025 | Driftwave Static on YourSpace.",
    "content_type": "video",
    "file_url": "https://img.youtube.com/vi/SpRiEmMulhg/hqdefault.jpg",
    "view_count": 49366,
    "like_count": 505,
    "created_at": "2025-12-20T21:50:03.536Z",
    "vibe_tags": [
      "chill",
      "futuristic"
    ]
  },
  {
    "id": "v37",
    "title": "Signalcon 2025 | Driftwave static - elite signal broadcast | Day 3",
    "description": "Watch Signalcon 2025 | Driftwave static - elite signal broadcast | Day 3 on YourSpace.",
    "content_type": "video",
    "file_url": "https://img.youtube.com/vi/94qI6WJeQSU/hqdefault.jpg",
    "view_count": 14432,
    "like_count": 3906,
    "created_at": "2026-01-06T11:19:53.366Z",
    "vibe_tags": [
      "futuristic",
      "retro"
    ]
  },
  {
    "id": "v38",
    "title": "Sofa king sad boi - = - Google how to cry",
    "description": "Watch Sofa king sad boi - = - Google how to cry on YourSpace.",
    "content_type": "video",
    "file_url": "https://img.youtube.com/vi/x4aO7zmHYec/hqdefault.jpg",
    "view_count": 27006,
    "like_count": 4582,
    "created_at": "2025-10-28T20:43:10.256Z",
    "vibe_tags": [
      "futuristic",
      "retro"
    ]
  },
  {
    "id": "v39",
    "title": "Slushwave | autumn‘s last breath of decaying slush | 12Matt3r visuals",
    "description": "Watch Slushwave | autumn‘s last breath of decaying slush | 12Matt3r visuals on YourSpace.",
    "content_type": "video",
    "file_url": "https://img.youtube.com/vi/GSrpDlrcHOg/hqdefault.jpg",
    "view_count": 5482,
    "like_count": 4465,
    "created_at": "2025-12-16T18:27:13.656Z",
    "vibe_tags": [
      "retro",
      "energetic"
    ]
  },
  {
    "id": "v40",
    "title": "@GlitchGuildUnited “Cyber Tape” @sofakingsadboi installation",
    "description": "Watch @GlitchGuildUnited “Cyber Tape” @sofakingsadboi installation on YourSpace.",
    "content_type": "video",
    "file_url": "https://img.youtube.com/vi/D9Cqm-kzooY/hqdefault.jpg",
    "view_count": 42332,
    "like_count": 1965,
    "created_at": "2025-11-01T07:23:58.692Z",
    "vibe_tags": [
      "energetic",
      "chill"
    ]
  },
  {
    "id": "v41",
    "title": "Sofa King Sad Boi - All alone in my house with some bad bitches - Visual Stimulants",
    "description": "Watch Sofa King Sad Boi - All alone in my house with some bad bitches - Visual Stimulants on YourSpace.",
    "content_type": "video",
    "file_url": "https://img.youtube.com/vi/xHAPpEaD5nM/hqdefault.jpg",
    "view_count": 34151,
    "like_count": 1271,
    "created_at": "2025-11-29T16:44:38.568Z",
    "vibe_tags": [
      "retro",
      "chill"
    ]
  },
  {
    "id": "v42",
    "title": "PRONEIIBLACK at blood sweat and beers 7",
    "description": "Watch PRONEIIBLACK at blood sweat and beers 7 on YourSpace.",
    "content_type": "video",
    "file_url": "https://img.youtube.com/vi/Xw_Xl-f2kXQ/hqdefault.jpg",
    "view_count": 38153,
    "like_count": 4147,
    "created_at": "2025-11-11T12:33:39.214Z",
    "vibe_tags": [
      "chill",
      "energetic"
    ]
  },
  {
    "id": "v43",
    "title": "Welcome To TrapCity Jerkanator live mix 1",
    "description": "Watch Welcome To TrapCity Jerkanator live mix 1 on YourSpace.",
    "content_type": "video",
    "file_url": "https://img.youtube.com/vi/kgvyAXDl-ss/hqdefault.jpg",
    "view_count": 44077,
    "like_count": 1266,
    "created_at": "2025-12-28T10:17:29.202Z",
    "vibe_tags": [
      "energetic",
      "chill"
    ]
  },
  {
    "id": "v44",
    "title": "Welcome To TrapCity Jerkanator live mix 2",
    "description": "Watch Welcome To TrapCity Jerkanator live mix 2 on YourSpace.",
    "content_type": "video",
    "file_url": "https://img.youtube.com/vi/6h9AHMSeoXk/hqdefault.jpg",
    "view_count": 19139,
    "like_count": 3593,
    "created_at": "2025-12-16T17:50:41.532Z",
    "vibe_tags": [
      "futuristic",
      "retro"
    ]
  },
  {
    "id": "v45",
    "title": "8/08 BASSHEAD CELEBRATION :: RAB LAB :: Sofa King Sad Boi :: visual stimulants",
    "description": "Watch 8/08 BASSHEAD CELEBRATION :: RAB LAB :: Sofa King Sad Boi :: visual stimulants on YourSpace.",
    "content_type": "video",
    "file_url": "https://img.youtube.com/vi/cef04kMXcEU/hqdefault.jpg",
    "view_count": 6770,
    "like_count": 735,
    "created_at": "2025-12-19T06:56:17.655Z",
    "vibe_tags": [
      "retro",
      "futuristic"
    ]
  },
  {
    "id": "v46",
    "title": "tanky johnson x 12matt3r enter the void 2025",
    "description": "Watch tanky johnson x 12matt3r enter the void 2025 on YourSpace.",
    "content_type": "video",
    "file_url": "https://img.youtube.com/vi/xYnauJbpdnc/hqdefault.jpg",
    "view_count": 43204,
    "like_count": 4922,
    "created_at": "2025-12-29T07:21:27.147Z",
    "vibe_tags": [
      "retro",
      "futuristic"
    ]
  },
  {
    "id": "v47",
    "title": "This AI Music Video is INSANE! SOFA KING SAD BOI x Chroma Awards | DATAMOSH EDM",
    "description": "Watch This AI Music Video is INSANE! SOFA KING SAD BOI x Chroma Awards | DATAMOSH EDM on YourSpace.",
    "content_type": "video",
    "file_url": "https://img.youtube.com/vi/EvpLAbOw7E4/hqdefault.jpg",
    "view_count": 19535,
    "like_count": 3209,
    "created_at": "2025-11-05T03:11:58.836Z",
    "vibe_tags": [
      "futuristic",
      "energetic"
    ]
  },
  {
    "id": "v48",
    "title": "Sunshines retribution - EXIT VALLEY",
    "description": "Watch Sunshines retribution - EXIT VALLEY on YourSpace.",
    "content_type": "video",
    "file_url": "https://img.youtube.com/vi/KLmPjAERXsI/hqdefault.jpg",
    "view_count": 41882,
    "like_count": 4805,
    "created_at": "2025-12-02T18:28:30.536Z",
    "vibe_tags": [
      "futuristic",
      "chill"
    ]
  },
  {
    "id": "v49",
    "title": "The Crawling Mind | Experimental AI Film - Chroma Awards Entry | SOFA KING SAD BOI",
    "description": "Watch The Crawling Mind | Experimental AI Film - Chroma Awards Entry | SOFA KING SAD BOI on YourSpace.",
    "content_type": "video",
    "file_url": "https://img.youtube.com/vi/FBaN4QWFucg/hqdefault.jpg",
    "view_count": 20903,
    "like_count": 991,
    "created_at": "2025-12-26T01:06:26.803Z",
    "vibe_tags": [
      "futuristic",
      "retro"
    ]
  },
  {
    "id": "v50",
    "title": "Wake up sunshine, it’s battle time!",
    "description": "Watch Wake up sunshine, it’s battle time! on YourSpace.",
    "content_type": "video",
    "file_url": "https://img.youtube.com/vi/i_8w65jOHu8/hqdefault.jpg",
    "view_count": 21640,
    "like_count": 1377,
    "created_at": "2026-01-07T02:28:03.223Z",
    "vibe_tags": [
      "retro",
      "energetic"
    ]
  },
  {
    "id": "v51",
    "title": "COWBOYS DON'T CRY | Tanky Johnson | Chroma Awards Entry | AI/VFX Music Video",
    "description": "Watch COWBOYS DON'T CRY | Tanky Johnson | Chroma Awards Entry | AI/VFX Music Video on YourSpace.",
    "content_type": "video",
    "file_url": "https://img.youtube.com/vi/1lAA395N8FE/hqdefault.jpg",
    "view_count": 24595,
    "like_count": 3086,
    "created_at": "2025-11-19T05:10:21.124Z",
    "vibe_tags": [
      "chill",
      "energetic"
    ]
  },
  {
    "id": "v52",
    "title": "NPC THERAPY GAME | CREDITS | CHROMA AWARDS | ai",
    "description": "Watch NPC THERAPY GAME | CREDITS | CHROMA AWARDS | ai on YourSpace.",
    "content_type": "video",
    "file_url": "https://img.youtube.com/vi/jfSAfMNQCNY/hqdefault.jpg",
    "view_count": 1074,
    "like_count": 4663,
    "created_at": "2025-10-16T08:24:25.252Z",
    "vibe_tags": [
      "chill",
      "energetic"
    ]
  },
  {
    "id": "v53",
    "title": "NPC THERAPY GAME | CHROMA AWARDS | EXPERIMENTAL AI GAME ENTRY",
    "description": "Watch NPC THERAPY GAME | CHROMA AWARDS | EXPERIMENTAL AI GAME ENTRY on YourSpace.",
    "content_type": "video",
    "file_url": "https://img.youtube.com/vi/dLWHNiePR8g/hqdefault.jpg",
    "view_count": 43521,
    "like_count": 245,
    "created_at": "2025-12-27T18:09:56.122Z",
    "vibe_tags": [
      "retro",
      "energetic"
    ]
  },
  {
    "id": "v54",
    "title": "Run Devil Run! | WIDDFAM | FRESH BLOOD | Sofa King Sad Boi",
    "description": "Watch Run Devil Run! | WIDDFAM | FRESH BLOOD | Sofa King Sad Boi on YourSpace.",
    "content_type": "video",
    "file_url": "https://img.youtube.com/vi/bt4V9bz8vMo/hqdefault.jpg",
    "view_count": 16503,
    "like_count": 999,
    "created_at": "2025-12-11T01:09:01.621Z",
    "vibe_tags": [
      "retro",
      "futuristic"
    ]
  },
  {
    "id": "v55",
    "title": "Driftwave Static - Run! DEVIL RUN!",
    "description": "Watch Driftwave Static - Run! DEVIL RUN! on YourSpace.",
    "content_type": "video",
    "file_url": "https://img.youtube.com/vi/mBi4wykQZPc/hqdefault.jpg",
    "view_count": 15207,
    "like_count": 2400,
    "created_at": "2025-10-13T16:44:49.222Z",
    "vibe_tags": [
      "chill",
      "futuristic"
    ]
  },
  {
    "id": "v56",
    "title": "🔥 Driving Vibes: ishowspeed & Sofa King Sad Boi's 2-Hour Drum & Bass Adventure! 🎵🚗",
    "description": "Watch 🔥 Driving Vibes: ishowspeed & Sofa King Sad Boi's 2-Hour Drum & Bass Adventure! 🎵🚗 on YourSpace.",
    "content_type": "video",
    "file_url": "https://img.youtube.com/vi/9JOClo_1NJE/hqdefault.jpg",
    "view_count": 43723,
    "like_count": 4079,
    "created_at": "2025-09-29T06:20:09.829Z",
    "vibe_tags": [
      "futuristic",
      "retro"
    ]
  },
  {
    "id": "v57",
    "title": "Mindbending AI hallucination Turns the Normal Into a Psychedelic Masterpiece",
    "description": "Watch Mindbending AI hallucination Turns the Normal Into a Psychedelic Masterpiece on YourSpace.",
    "content_type": "video",
    "file_url": "https://img.youtube.com/vi/eiP06YHseow/hqdefault.jpg",
    "view_count": 50614,
    "like_count": 1303,
    "created_at": "2025-12-25T17:41:10.263Z",
    "vibe_tags": [
      "retro",
      "energetic"
    ]
  },
  {
    "id": "v58",
    "title": "Tipper & Friends Final Chapter Competition 2025 | Sofa Sauce",
    "description": "Watch Tipper & Friends Final Chapter Competition 2025 | Sofa Sauce on YourSpace.",
    "content_type": "video",
    "file_url": "https://img.youtube.com/vi/dNTeLDJeQq8/hqdefault.jpg",
    "view_count": 12111,
    "like_count": 338,
    "created_at": "2025-10-02T08:18:45.925Z",
    "vibe_tags": [
      "chill",
      "energetic"
    ]
  },
  {
    "id": "v59",
    "title": "Cartman Covers \"That Guy\" | Tyler, the Creator Remix of Kendrick Lamar | South Park Parody",
    "description": "Watch Cartman Covers \"That Guy\" | Tyler, the Creator Remix of Kendrick Lamar | South Park Parody on YourSpace.",
    "content_type": "video",
    "file_url": "https://img.youtube.com/vi/lqB_2TGkWd0/hqdefault.jpg",
    "view_count": 28667,
    "like_count": 1567,
    "created_at": "2025-09-22T23:31:27.542Z",
    "vibe_tags": [
      "futuristic",
      "retro"
    ]
  },
  {
    "id": "v60",
    "title": "Incredibox Sprunki - Be Like You (Horror Skunx x Sofa Sauce)",
    "description": "Watch Incredibox Sprunki - Be Like You (Horror Skunx x Sofa Sauce) on YourSpace.",
    "content_type": "video",
    "file_url": "https://img.youtube.com/vi/f6x9ebrVKN4/hqdefault.jpg",
    "view_count": 1317,
    "like_count": 2587,
    "created_at": "2026-01-01T03:01:46.417Z",
    "vibe_tags": [
      "retro",
      "futuristic"
    ]
  },
  {
    "id": "v61",
    "title": "Lil Ko1by and Sofa King Sad Boi's Top Secret to MAXIMUM Ring Boosting!",
    "description": "Watch Lil Ko1by and Sofa King Sad Boi's Top Secret to MAXIMUM Ring Boosting! on YourSpace.",
    "content_type": "video",
    "file_url": "https://img.youtube.com/vi/AUk7thgP1xA/hqdefault.jpg",
    "view_count": 15145,
    "like_count": 3093,
    "created_at": "2025-10-25T23:44:49.563Z",
    "vibe_tags": [
      "chill",
      "energetic"
    ]
  },
  {
    "id": "v62",
    "title": "3 MIND-BLOWING horror skunx Dubstep SPRUNKI Remixes You Need to Hear NOW",
    "description": "Watch 3 MIND-BLOWING horror skunx Dubstep SPRUNKI Remixes You Need to Hear NOW on YourSpace.",
    "content_type": "video",
    "file_url": "https://img.youtube.com/vi/fSV5ss4QLn0/hqdefault.jpg",
    "view_count": 3551,
    "like_count": 2647,
    "created_at": "2025-10-05T11:19:58.749Z",
    "vibe_tags": [
      "energetic",
      "futuristic"
    ]
  },
  {
    "id": "v63",
    "title": "Horror Skunx Incredibox Freaky Sprunki Song Remix",
    "description": "Watch Horror Skunx Incredibox Freaky Sprunki Song Remix on YourSpace.",
    "content_type": "video",
    "file_url": "https://img.youtube.com/vi/cEaI7ZB1Yt0/hqdefault.jpg",
    "view_count": 39615,
    "like_count": 4210,
    "created_at": "2025-10-26T03:43:59.703Z",
    "vibe_tags": [
      "retro",
      "energetic"
    ]
  },
  {
    "id": "v64",
    "title": "TBH Beat Challenge-Collard Greens with a side of Brain rot-",
    "description": "Watch TBH Beat Challenge-Collard Greens with a side of Brain rot- on YourSpace.",
    "content_type": "video",
    "file_url": "https://img.youtube.com/vi/WND0u3s5mXI/hqdefault.jpg",
    "view_count": 14051,
    "like_count": 740,
    "created_at": "2025-10-14T06:37:27.795Z",
    "vibe_tags": [
      "chill",
      "energetic"
    ]
  },
  {
    "id": "v65",
    "title": "Lofi Road Into The Sun NYE Miami Mix | Sofa King Sad Boi | Bassnectar Tribute",
    "description": "Watch Lofi Road Into The Sun NYE Miami Mix | Sofa King Sad Boi | Bassnectar Tribute on YourSpace.",
    "content_type": "video",
    "file_url": "https://img.youtube.com/vi/3z8anmnli3I/hqdefault.jpg",
    "view_count": 11051,
    "like_count": 4811,
    "created_at": "2025-11-24T03:34:30.383Z",
    "vibe_tags": [
      "energetic",
      "chill"
    ]
  },
  {
    "id": "v66",
    "title": "Surviving the Worst Life Raft Scenario EVER! While hallucinating!",
    "description": "Watch Surviving the Worst Life Raft Scenario EVER! While hallucinating! on YourSpace.",
    "content_type": "video",
    "file_url": "https://img.youtube.com/vi/Vpkl5OMEna0/hqdefault.jpg",
    "view_count": 14501,
    "like_count": 865,
    "created_at": "2025-11-15T16:23:41.020Z",
    "vibe_tags": [
      "chill",
      "energetic"
    ]
  },
  {
    "id": "v67",
    "title": "Certified most unhinged Suwannee Lofi ￼ COUCHfam, Hammock squad, imaginary totem storytime anthem",
    "description": "Watch Certified most unhinged Suwannee Lofi ￼ COUCHfam, Hammock squad, imaginary totem storytime anthem on YourSpace.",
    "content_type": "video",
    "file_url": "https://img.youtube.com/vi/K03ZuRjcMoc/hqdefault.jpg",
    "view_count": 8128,
    "like_count": 878,
    "created_at": "2025-09-20T11:52:43.997Z",
    "vibe_tags": [
      "chill",
      "energetic"
    ]
  },
  {
    "id": "v68",
    "title": "NOEMOTION vs Emotion Who Wins?",
    "description": "Watch NOEMOTION vs Emotion Who Wins? on YourSpace.",
    "content_type": "video",
    "file_url": "https://img.youtube.com/vi/QQVctj8dC5U/hqdefault.jpg",
    "view_count": 46197,
    "like_count": 1511,
    "created_at": "2025-12-21T14:36:06.594Z",
    "vibe_tags": [
      "chill",
      "energetic"
    ]
  },
  {
    "id": "v69",
    "title": "Tipper - Life Raft for a Death trip (Sofa Sauce)",
    "description": "Watch Tipper - Life Raft for a Death trip (Sofa Sauce) on YourSpace.",
    "content_type": "video",
    "file_url": "https://img.youtube.com/vi/6IXP94xJEzY/hqdefault.jpg",
    "view_count": 44095,
    "like_count": 3240,
    "created_at": "2025-12-06T14:19:46.734Z",
    "vibe_tags": [
      "chill",
      "energetic"
    ]
  },
  {
    "id": "v70",
    "title": "Lofi Wook Hop Celebration: A Tribute to Dave Tipper and His Tribe!",
    "description": "Watch Lofi Wook Hop Celebration: A Tribute to Dave Tipper and His Tribe! on YourSpace.",
    "content_type": "video",
    "file_url": "https://img.youtube.com/vi/HIpHoAr3c_w/hqdefault.jpg",
    "view_count": 29558,
    "like_count": 1913,
    "created_at": "2025-10-15T09:00:30.921Z",
    "vibe_tags": [
      "futuristic",
      "chill"
    ]
  },
  {
    "id": "v71",
    "title": "Tipper-Mason | Sofa lOFI Sauce",
    "description": "Watch Tipper-Mason | Sofa lOFI Sauce on YourSpace.",
    "content_type": "video",
    "file_url": "https://img.youtube.com/vi/ykDQJXe5q8o/hqdefault.jpg",
    "view_count": 37976,
    "like_count": 3461,
    "created_at": "2025-12-01T23:07:21.262Z",
    "vibe_tags": [
      "chill",
      "energetic"
    ]
  },
  {
    "id": "v72",
    "title": "Saturaided Saturdaze 7 13 24 sofa sessions",
    "description": "Watch Saturaided Saturdaze 7 13 24 sofa sessions on YourSpace.",
    "content_type": "video",
    "file_url": "https://img.youtube.com/vi/WFw1ITBslmY/hqdefault.jpg",
    "view_count": 19093,
    "like_count": 427,
    "created_at": "2025-10-12T03:07:00.323Z",
    "vibe_tags": [
      "futuristic",
      "chill"
    ]
  },
  {
    "id": "v73",
    "title": "Saturaided with 12matt3r ft Noemotion Goldmask/Glitch art And all unreleased music",
    "description": "Watch Saturaided with 12matt3r ft Noemotion Goldmask/Glitch art And all unreleased music on YourSpace.",
    "content_type": "video",
    "file_url": "https://img.youtube.com/vi/_n1hSSqBVg8/hqdefault.jpg",
    "view_count": 40359,
    "like_count": 4747,
    "created_at": "2025-10-16T20:56:38.206Z",
    "vibe_tags": [
      "energetic",
      "futuristic"
    ]
  },
  {
    "id": "v74",
    "title": "Slushwave Social Club's Brief Glimpses of Quicksilver Dreams",
    "description": "Watch Slushwave Social Club's Brief Glimpses of Quicksilver Dreams on YourSpace.",
    "content_type": "video",
    "file_url": "https://img.youtube.com/vi/7IU8D_1y4W4/hqdefault.jpg",
    "view_count": 22465,
    "like_count": 204,
    "created_at": "2026-01-05T02:30:46.323Z",
    "vibe_tags": [
      "futuristic",
      "retro"
    ]
  },
  {
    "id": "v75",
    "title": "02/09/24 iPad cam",
    "description": "Watch 02/09/24 iPad cam on YourSpace.",
    "content_type": "video",
    "file_url": "https://img.youtube.com/vi/B4RoawWO1JI/hqdefault.jpg",
    "view_count": 26114,
    "like_count": 4813,
    "created_at": "2025-11-09T17:28:28.837Z",
    "vibe_tags": [
      "chill",
      "energetic"
    ]
  },
  {
    "id": "v76",
    "title": "Pooty x 1.9.9.9 - Enter the phonk (12matt3r Visuals)",
    "description": "Watch Pooty x 1.9.9.9 - Enter the phonk (12matt3r Visuals) on YourSpace.",
    "content_type": "video",
    "file_url": "https://img.youtube.com/vi/82_Ju3i-NZU/hqdefault.jpg",
    "view_count": 25360,
    "like_count": 4569,
    "created_at": "2025-12-29T10:35:31.583Z",
    "vibe_tags": [
      "futuristic",
      "retro"
    ]
  },
  {
    "id": "v77",
    "title": "The Enigmatic Harmony of Kaiber AI & 12matt3r Psychedelia",
    "description": "Watch The Enigmatic Harmony of Kaiber AI & 12matt3r Psychedelia on YourSpace.",
    "content_type": "video",
    "file_url": "https://img.youtube.com/vi/C46ATeslaD4/hqdefault.jpg",
    "view_count": 29848,
    "like_count": 3865,
    "created_at": "2025-12-23T14:46:39.561Z",
    "vibe_tags": [
      "chill",
      "energetic"
    ]
  },
  {
    "id": "v78",
    "title": "GreatOwl - Ĉiela Fajro (The Rendezvous Headnod Minimix) 2024",
    "description": "Watch GreatOwl - Ĉiela Fajro (The Rendezvous Headnod Minimix) 2024 on YourSpace.",
    "content_type": "video",
    "file_url": "https://img.youtube.com/vi/IScVYfJ8UX8/hqdefault.jpg",
    "view_count": 40581,
    "like_count": 4824,
    "created_at": "2025-10-29T10:33:42.317Z",
    "vibe_tags": [
      "futuristic",
      "retro"
    ]
  },
  {
    "id": "v79",
    "title": "Pooty - Resurgence (12matt3r Visuals)",
    "description": "Watch Pooty - Resurgence (12matt3r Visuals) on YourSpace.",
    "content_type": "video",
    "file_url": "https://img.youtube.com/vi/QATIBFburPc/hqdefault.jpg",
    "view_count": 14591,
    "like_count": 3190,
    "created_at": "2025-10-02T00:38:48.515Z",
    "vibe_tags": [
      "chill",
      "energetic"
    ]
  },
  {
    "id": "v80",
    "title": "Equipoise - Are We Dreaming?",
    "description": "Watch Equipoise - Are We Dreaming? on YourSpace.",
    "content_type": "video",
    "file_url": "https://img.youtube.com/vi/Vc9KMt-9WR0/hqdefault.jpg",
    "view_count": 7921,
    "like_count": 2571,
    "created_at": "2025-10-14T10:04:42.591Z",
    "vibe_tags": [
      "chill",
      "energetic"
    ]
  },
  {
    "id": "v81",
    "title": "Matilda :: but you took mushrooms a little bit ago and yourestartingtohaveabadtripVISUAL STIMULANTS",
    "description": "Watch Matilda :: but you took mushrooms a little bit ago and yourestartingtohaveabadtripVISUAL STIMULANTS on YourSpace.",
    "content_type": "video",
    "file_url": "https://img.youtube.com/vi/VmJSbTOy2DA/hqdefault.jpg",
    "view_count": 33836,
    "like_count": 1792,
    "created_at": "2025-10-05T16:02:41.261Z",
    "vibe_tags": [
      "futuristic",
      "chill"
    ]
  },
  {
    "id": "v82",
    "title": "Mind-Blowing Glitch Art: Unveiling the Secrets of Adult Swim's Analog Video",
    "description": "Watch Mind-Blowing Glitch Art: Unveiling the Secrets of Adult Swim's Analog Video on YourSpace.",
    "content_type": "video",
    "file_url": "https://img.youtube.com/vi/Bm-Tg-gDuVY/hqdefault.jpg",
    "view_count": 8301,
    "like_count": 4740,
    "created_at": "2025-11-17T16:04:37.842Z",
    "vibe_tags": [
      "retro",
      "energetic"
    ]
  },
  {
    "id": "v83",
    "title": "Visual Stimulants :: Sofa King Sad Boi :: Winning Space Jesus Competition Mix",
    "description": "Watch Visual Stimulants :: Sofa King Sad Boi :: Winning Space Jesus Competition Mix on YourSpace.",
    "content_type": "video",
    "file_url": "https://img.youtube.com/vi/iZcW6z8Lm0g/hqdefault.jpg",
    "view_count": 41780,
    "like_count": 3150,
    "created_at": "2025-10-17T14:18:18.864Z",
    "vibe_tags": [
      "chill",
      "energetic"
    ]
  },
  {
    "id": "v84",
    "title": "Sofa king Sad Boi - Hey yo Eww - Grand Theft Kaiber",
    "description": "Watch Sofa king Sad Boi - Hey yo Eww - Grand Theft Kaiber on YourSpace.",
    "content_type": "video",
    "file_url": "https://img.youtube.com/vi/_CfjBPX3UQc/hqdefault.jpg",
    "view_count": 19118,
    "like_count": 4624,
    "created_at": "2025-12-26T20:09:43.187Z",
    "vibe_tags": [
      "retro",
      "futuristic"
    ]
  },
  {
    "id": "v85",
    "title": "I did it all for the womp",
    "description": "Watch I did it all for the womp on YourSpace.",
    "content_type": "video",
    "file_url": "https://img.youtube.com/vi/OxnIzaF-ZT8/hqdefault.jpg",
    "view_count": 28181,
    "like_count": 3423,
    "created_at": "2025-11-17T05:28:35.786Z",
    "vibe_tags": [
      "energetic",
      "chill"
    ]
  },
  {
    "id": "v86",
    "title": "Moonsshine was an inside job - sofa king sad boi #kaiberai",
    "description": "Watch Moonsshine was an inside job - sofa king sad boi #kaiberai on YourSpace.",
    "content_type": "video",
    "file_url": "https://img.youtube.com/vi/1w_ErfKbgg4/hqdefault.jpg",
    "view_count": 44443,
    "like_count": 430,
    "created_at": "2025-09-28T22:13:09.043Z",
    "vibe_tags": [
      "futuristic",
      "retro"
    ]
  },
  {
    "id": "v87",
    "title": "Pink Floyd Gave Me Brain Damage #kaiberai",
    "description": "Watch Pink Floyd Gave Me Brain Damage #kaiberai on YourSpace.",
    "content_type": "video",
    "file_url": "https://img.youtube.com/vi/3t1CXmmsbgM/hqdefault.jpg",
    "view_count": 16641,
    "like_count": 2619,
    "created_at": "2026-01-01T17:03:38.516Z",
    "vibe_tags": [
      "retro",
      "energetic"
    ]
  },
  {
    "id": "v88",
    "title": "Iggy azalea - emo club anthem ( sofa king sad boi )",
    "description": "Watch Iggy azalea - emo club anthem ( sofa king sad boi ) on YourSpace.",
    "content_type": "video",
    "file_url": "https://img.youtube.com/vi/Av_l90Syomc/hqdefault.jpg",
    "view_count": 36999,
    "like_count": 3833,
    "created_at": "2025-11-12T03:33:42.707Z",
    "vibe_tags": [
      "chill",
      "energetic"
    ]
  },
  {
    "id": "v89",
    "title": "sofa king sad boi - smile so it doesnt get weird",
    "description": "Watch sofa king sad boi - smile so it doesnt get weird on YourSpace.",
    "content_type": "video",
    "file_url": "https://img.youtube.com/vi/uy4JuA3GoFI/hqdefault.jpg",
    "view_count": 21179,
    "like_count": 151,
    "created_at": "2025-12-26T04:41:07.573Z",
    "vibe_tags": [
      "chill",
      "energetic"
    ]
  },
  {
    "id": "v90",
    "title": "Bassnectar - Prayer Song ft. Una & Wicahpi & Merle",
    "description": "Watch Bassnectar - Prayer Song ft. Una & Wicahpi & Merle on YourSpace.",
    "content_type": "video",
    "file_url": "https://img.youtube.com/vi/nwRLYrcPck8/hqdefault.jpg",
    "view_count": 8751,
    "like_count": 155,
    "created_at": "2025-10-10T22:48:11.117Z",
    "vibe_tags": [
      "futuristic",
      "chill"
    ]
  },
  {
    "id": "v91",
    "title": "Bassnectar - Time for some action (Rave Charles Reflection)",
    "description": "Watch Bassnectar - Time for some action (Rave Charles Reflection) on YourSpace.",
    "content_type": "video",
    "file_url": "https://img.youtube.com/vi/TW6LdoV6obY/hqdefault.jpg",
    "view_count": 45009,
    "like_count": 1458,
    "created_at": "2026-01-12T06:43:18.791Z",
    "vibe_tags": [
      "futuristic",
      "retro"
    ]
  },
  {
    "id": "v92",
    "title": "Replay-Sofa King Sad Boi",
    "description": "Watch Replay-Sofa King Sad Boi on YourSpace.",
    "content_type": "video",
    "file_url": "https://img.youtube.com/vi/iaSX-6kJ6m0/hqdefault.jpg",
    "view_count": 27260,
    "like_count": 1552,
    "created_at": "2025-10-17T22:25:06.929Z",
    "vibe_tags": [
      "futuristic",
      "energetic"
    ]
  },
  {
    "id": "v93",
    "title": "Porter Robinson - look at the sky (EastlandPhuks)",
    "description": "Watch Porter Robinson - look at the sky (EastlandPhuks) on YourSpace.",
    "content_type": "video",
    "file_url": "https://img.youtube.com/vi/lrJ5AJ2WWLo/hqdefault.jpg",
    "view_count": 49161,
    "like_count": 4443,
    "created_at": "2026-01-10T22:06:48.006Z",
    "vibe_tags": [
      "futuristic",
      "chill"
    ]
  },
  {
    "id": "v94",
    "title": "Welcome home -TOS Radio - Rave Charles",
    "description": "Watch Welcome home -TOS Radio - Rave Charles on YourSpace.",
    "content_type": "video",
    "file_url": "https://img.youtube.com/vi/2Zm9Byj2foc/hqdefault.jpg",
    "view_count": 5034,
    "like_count": 1557,
    "created_at": "2025-11-03T16:24:06.046Z",
    "vibe_tags": [
      "energetic",
      "futuristic"
    ]
  },
  {
    "id": "v95",
    "title": "12matt3r Super troopers intro kaiber ai transformation",
    "description": "Watch 12matt3r Super troopers intro kaiber ai transformation on YourSpace.",
    "content_type": "video",
    "file_url": "https://img.youtube.com/vi/-_D1X9k6Y8k/hqdefault.jpg",
    "view_count": 12233,
    "like_count": 4127,
    "created_at": "2025-10-26T08:22:21.370Z",
    "vibe_tags": [
      "energetic",
      "chill"
    ]
  },
  {
    "id": "v96",
    "title": "Rick and Morty - Reaction - Kaiber Ai - 12matt3r - first time watching",
    "description": "Watch Rick and Morty - Reaction - Kaiber Ai - 12matt3r - first time watching on YourSpace.",
    "content_type": "video",
    "file_url": "https://img.youtube.com/vi/pEjCXDhr28A/hqdefault.jpg",
    "view_count": 34354,
    "like_count": 1469,
    "created_at": "2025-12-09T06:43:36.084Z",
    "vibe_tags": [
      "chill",
      "energetic"
    ]
  },
  {
    "id": "v97",
    "title": "Tipper-Dreamsters(all the way back)",
    "description": "Watch Tipper-Dreamsters(all the way back) on YourSpace.",
    "content_type": "video",
    "file_url": "https://img.youtube.com/vi/4oNPSeYeriw/hqdefault.jpg",
    "view_count": 34055,
    "like_count": 950,
    "created_at": "2025-12-02T03:04:00.799Z",
    "vibe_tags": [
      "retro",
      "chill"
    ]
  },
  {
    "id": "v98",
    "title": "VIZ_WEL.TV PREMIERE 24 HOUR STREAM 12MATT3R SUNRISE CEREMONY",
    "description": "Watch VIZ_WEL.TV PREMIERE 24 HOUR STREAM 12MATT3R SUNRISE CEREMONY on YourSpace.",
    "content_type": "video",
    "file_url": "https://img.youtube.com/vi/DbQ7BBVUwR0/hqdefault.jpg",
    "view_count": 46138,
    "like_count": 1590,
    "created_at": "2025-10-06T10:30:42.729Z",
    "vibe_tags": [
      "futuristic",
      "energetic"
    ]
  },
  {
    "id": "v99",
    "title": "Trippy visuals Tipper Sunrise 12Matt3r Homage VIZ_WEL.TV",
    "description": "Watch Trippy visuals Tipper Sunrise 12Matt3r Homage VIZ_WEL.TV on YourSpace.",
    "content_type": "video",
    "file_url": "https://img.youtube.com/vi/2G66cZBJJn0/hqdefault.jpg",
    "view_count": 40664,
    "like_count": 297,
    "created_at": "2025-10-17T13:02:44.787Z",
    "vibe_tags": [
      "energetic",
      "retro"
    ]
  },
  {
    "id": "v100",
    "title": "Visual Stimulants 12Matt3r",
    "description": "Watch Visual Stimulants 12Matt3r on YourSpace.",
    "content_type": "video",
    "file_url": "https://img.youtube.com/vi/cXRzJe43QOs/hqdefault.jpg",
    "view_count": 11905,
    "like_count": 1065,
    "created_at": "2025-10-10T23:43:44.363Z",
    "vibe_tags": [
      "futuristic",
      "retro"
    ]
  },
  {
    "id": "v101",
    "title": "Visual Stimulants 12Matt3r",
    "description": "Watch Visual Stimulants 12Matt3r on YourSpace.",
    "content_type": "video",
    "file_url": "https://img.youtube.com/vi/2-l3ewvUuS0/hqdefault.jpg",
    "view_count": 19178,
    "like_count": 3792,
    "created_at": "2025-10-18T15:51:28.118Z",
    "vibe_tags": [
      "futuristic",
      "chill"
    ]
  },
  {
    "id": "v102",
    "title": "Visual Stimulants 12Matt3r",
    "description": "Watch Visual Stimulants 12Matt3r on YourSpace.",
    "content_type": "video",
    "file_url": "https://img.youtube.com/vi/auIA1dYCduo/hqdefault.jpg",
    "view_count": 26418,
    "like_count": 2633,
    "created_at": "2025-11-21T10:35:27.218Z",
    "vibe_tags": [
      "futuristic",
      "chill"
    ]
  },
  {
    "id": "v103",
    "title": "Ernest's Mind-Blowing Journey with Visual Stimulants",
    "description": "Watch Ernest's Mind-Blowing Journey with Visual Stimulants on YourSpace.",
    "content_type": "video",
    "file_url": "https://img.youtube.com/vi/eaDlq3PTubI/hqdefault.jpg",
    "view_count": 26981,
    "like_count": 2400,
    "created_at": "2025-09-25T19:15:35.136Z",
    "vibe_tags": [
      "chill",
      "retro"
    ]
  },
  {
    "id": "v104",
    "title": "@Flume Highest Building #kaiberai #trippyshorts #flume",
    "description": "Watch @Flume Highest Building #kaiberai #trippyshorts #flume on YourSpace.",
    "content_type": "video",
    "file_url": "https://img.youtube.com/vi/PKej9WcXUHY/hqdefault.jpg",
    "view_count": 8884,
    "like_count": 1504,
    "created_at": "2026-01-01T07:19:28.982Z",
    "vibe_tags": [
      "chill",
      "energetic"
    ]
  },
  {
    "id": "v105",
    "title": "Epic Close Encounters: Space Jesus x Glass Animals x Post Malone",
    "description": "Watch Epic Close Encounters: Space Jesus x Glass Animals x Post Malone on YourSpace.",
    "content_type": "video",
    "file_url": "https://img.youtube.com/vi/QuiQBkXrews/hqdefault.jpg",
    "view_count": 4844,
    "like_count": 4976,
    "created_at": "2025-09-23T10:35:23.811Z",
    "vibe_tags": [
      "chill",
      "futuristic"
    ]
  },
  {
    "id": "v106",
    "title": "Fear and loathing in Las Vegas trippy remix",
    "description": "Watch Fear and loathing in Las Vegas trippy remix on YourSpace.",
    "content_type": "video",
    "file_url": "https://img.youtube.com/vi/i4F4sNk3JBs/hqdefault.jpg",
    "view_count": 18118,
    "like_count": 3523,
    "created_at": "2026-01-11T02:35:26.525Z",
    "vibe_tags": [
      "chill",
      "energetic"
    ]
  },
  {
    "id": "v107",
    "title": "12Matt3r Retexture",
    "description": "Watch 12Matt3r Retexture on YourSpace.",
    "content_type": "video",
    "file_url": "https://img.youtube.com/vi/LLxJKprvzKE/hqdefault.jpg",
    "view_count": 23326,
    "like_count": 1138,
    "created_at": "2025-10-28T03:36:48.939Z",
    "vibe_tags": [
      "chill",
      "retro"
    ]
  },
  {
    "id": "v108",
    "title": "12Matt3r Retexture",
    "description": "Watch 12Matt3r Retexture on YourSpace.",
    "content_type": "video",
    "file_url": "https://img.youtube.com/vi/PJzwF9zrWGU/hqdefault.jpg",
    "view_count": 5373,
    "like_count": 716,
    "created_at": "2026-01-05T17:21:43.876Z",
    "vibe_tags": [
      "chill",
      "energetic"
    ]
  },
  {
    "id": "v109",
    "title": "12Matt3r Retexture",
    "description": "Watch 12Matt3r Retexture on YourSpace.",
    "content_type": "video",
    "file_url": "https://img.youtube.com/vi/Ro-5D7qm5x8/hqdefault.jpg",
    "view_count": 1818,
    "like_count": 2638,
    "created_at": "2025-11-05T07:24:19.922Z",
    "vibe_tags": [
      "chill",
      "energetic"
    ]
  },
  {
    "id": "v110",
    "title": "12Matt3r Retexture",
    "description": "Watch 12Matt3r Retexture on YourSpace.",
    "content_type": "video",
    "file_url": "https://img.youtube.com/vi/PeZ7ua_9id0/hqdefault.jpg",
    "view_count": 40120,
    "like_count": 2971,
    "created_at": "2025-10-04T06:45:34.022Z",
    "vibe_tags": [
      "futuristic",
      "energetic"
    ]
  },
  {
    "id": "v111",
    "title": "12Matt3r Retexture",
    "description": "Watch 12Matt3r Retexture on YourSpace.",
    "content_type": "video",
    "file_url": "https://img.youtube.com/vi/lnGmB630ZE0/hqdefault.jpg",
    "view_count": 21883,
    "like_count": 501,
    "created_at": "2025-12-30T07:09:24.854Z",
    "vibe_tags": [
      "chill",
      "energetic"
    ]
  },
  {
    "id": "v112",
    "title": "12Matt3r Retexture",
    "description": "Watch 12Matt3r Retexture on YourSpace.",
    "content_type": "video",
    "file_url": "https://img.youtube.com/vi/k5NeJcwHXdQ/hqdefault.jpg",
    "view_count": 49765,
    "like_count": 222,
    "created_at": "2025-11-11T09:53:05.328Z",
    "vibe_tags": [
      "futuristic",
      "chill"
    ]
  },
  {
    "id": "v113",
    "title": "12Matt3r Retexture",
    "description": "Watch 12Matt3r Retexture on YourSpace.",
    "content_type": "video",
    "file_url": "https://img.youtube.com/vi/gXC6JXu9KHM/hqdefault.jpg",
    "view_count": 20377,
    "like_count": 960,
    "created_at": "2025-12-15T20:47:31.112Z",
    "vibe_tags": [
      "futuristic",
      "chill"
    ]
  },
  {
    "id": "v114",
    "title": "12Matt3r Retexture",
    "description": "Watch 12Matt3r Retexture on YourSpace.",
    "content_type": "video",
    "file_url": "https://img.youtube.com/vi/IElpXImJ_YE/hqdefault.jpg",
    "view_count": 7341,
    "like_count": 1006,
    "created_at": "2025-10-13T00:55:14.554Z",
    "vibe_tags": [
      "futuristic",
      "retro"
    ]
  },
  {
    "id": "v115",
    "title": "12Matt3r Retexture",
    "description": "Watch 12Matt3r Retexture on YourSpace.",
    "content_type": "video",
    "file_url": "https://img.youtube.com/vi/F4EVUJ-rZDs/hqdefault.jpg",
    "view_count": 13621,
    "like_count": 4031,
    "created_at": "2025-09-24T15:54:46.776Z",
    "vibe_tags": [
      "retro",
      "energetic"
    ]
  },
  {
    "id": "v116",
    "title": "Dive into Big Splash 2023: The Most Anticipated unofficial Adult Swim Event",
    "description": "Watch Dive into Big Splash 2023: The Most Anticipated unofficial Adult Swim Event on YourSpace.",
    "content_type": "video",
    "file_url": "https://img.youtube.com/vi/IRjquCG9fAg/hqdefault.jpg",
    "view_count": 27495,
    "like_count": 3378,
    "created_at": "2025-09-28T09:16:24.588Z",
    "vibe_tags": [
      "energetic",
      "chill"
    ]
  },
  {
    "id": "v117",
    "title": "@glitchguild weekly challenge “ Microscopic”￼osmosis jones",
    "description": "Watch @glitchguild weekly challenge “ Microscopic”￼osmosis jones on YourSpace.",
    "content_type": "video",
    "file_url": "https://img.youtube.com/vi/SrTL5p9u1zg/hqdefault.jpg",
    "view_count": 2318,
    "like_count": 3656,
    "created_at": "2025-12-27T21:42:55.852Z",
    "vibe_tags": [
      "energetic",
      "futuristic"
    ]
  },
  {
    "id": "v118",
    "title": "Levity flip it remix (sofa king sad boi) Elevator flip",
    "description": "Watch Levity flip it remix (sofa king sad boi) Elevator flip on YourSpace.",
    "content_type": "video",
    "file_url": "https://img.youtube.com/vi/bf-xNbOiK-M/hqdefault.jpg",
    "view_count": 30827,
    "like_count": 2847,
    "created_at": "2025-11-03T05:10:47.494Z",
    "vibe_tags": [
      "chill",
      "futuristic"
    ]
  },
  {
    "id": "v119",
    "title": "Noemotion Goldmask - championship title song (Lofi Remix) Listening Party #38",
    "description": "Watch Noemotion Goldmask - championship title song (Lofi Remix) Listening Party #38 on YourSpace.",
    "content_type": "video",
    "file_url": "https://img.youtube.com/vi/q2RJ3Z4QyuM/hqdefault.jpg",
    "view_count": 42996,
    "like_count": 1641,
    "created_at": "2025-11-10T23:07:10.849Z",
    "vibe_tags": [
      "futuristic",
      "energetic"
    ]
  },
  {
    "id": "v120",
    "title": "@GlitchGuildUnited weekly prompt “ microscopic “￼",
    "description": "Watch @GlitchGuildUnited weekly prompt “ microscopic “￼ on YourSpace.",
    "content_type": "video",
    "file_url": "https://img.youtube.com/vi/FULBuf03-64/hqdefault.jpg",
    "view_count": 11429,
    "like_count": 4464,
    "created_at": "2025-12-22T06:23:11.096Z",
    "vibe_tags": [
      "futuristic",
      "retro"
    ]
  },
  {
    "id": "v121",
    "title": "@GlitchGuildUnited weekly prompt “feedback”",
    "description": "Watch @GlitchGuildUnited weekly prompt “feedback” on YourSpace.",
    "content_type": "video",
    "file_url": "https://img.youtube.com/vi/wPwSyGFwriU/hqdefault.jpg",
    "view_count": 9730,
    "like_count": 5055,
    "created_at": "2025-10-22T04:00:33.450Z",
    "vibe_tags": [
      "energetic",
      "retro"
    ]
  },
  {
    "id": "v122",
    "title": "@GlitchGuildUnited weekly prompt “cybertape bumpers”",
    "description": "Watch @GlitchGuildUnited weekly prompt “cybertape bumpers” on YourSpace.",
    "content_type": "video",
    "file_url": "https://img.youtube.com/vi/0YdEtFmxJHg/hqdefault.jpg",
    "view_count": 31438,
    "like_count": 4508,
    "created_at": "2025-12-13T07:56:57.424Z",
    "vibe_tags": [
      "retro",
      "futuristic"
    ]
  },
  {
    "id": "v123",
    "title": "@GlitchGuildUnited weekly prompt “y2k”",
    "description": "Watch @GlitchGuildUnited weekly prompt “y2k” on YourSpace.",
    "content_type": "video",
    "file_url": "https://img.youtube.com/vi/py8m0tYTK-k/hqdefault.jpg",
    "view_count": 33342,
    "like_count": 1423,
    "created_at": "2025-12-14T20:56:09.876Z",
    "vibe_tags": [
      "chill",
      "energetic"
    ]
  },
  {
    "id": "v124",
    "title": "Bassnectar A New Horizon Night One Cooldown MIX",
    "description": "Watch Bassnectar A New Horizon Night One Cooldown MIX on YourSpace.",
    "content_type": "video",
    "file_url": "https://img.youtube.com/vi/kR8MYn5-oNg/hqdefault.jpg",
    "view_count": 33459,
    "like_count": 2633,
    "created_at": "2025-11-14T20:16:01.129Z",
    "vibe_tags": [
      "futuristic",
      "retro"
    ]
  },
  {
    "id": "v125",
    "title": "lil Peep x marshmello - Spotlight Dubstep remix Eazy-E & Eminem |",
    "description": "Watch lil Peep x marshmello - Spotlight Dubstep remix Eazy-E & Eminem | on YourSpace.",
    "content_type": "video",
    "file_url": "https://img.youtube.com/vi/qjHtNtIpc_E/hqdefault.jpg",
    "view_count": 6092,
    "like_count": 1786,
    "created_at": "2025-10-16T20:23:19.478Z",
    "vibe_tags": [
      "futuristic",
      "retro"
    ]
  },
  {
    "id": "v126",
    "title": "Unveiling the Secret name of NoEmotion GoldMask {Sofa Sauce}",
    "description": "Watch Unveiling the Secret name of NoEmotion GoldMask {Sofa Sauce} on YourSpace.",
    "content_type": "video",
    "file_url": "https://img.youtube.com/vi/_Y4fLhGpm68/hqdefault.jpg",
    "view_count": 32397,
    "like_count": 2200,
    "created_at": "2025-12-17T01:17:41.117Z",
    "vibe_tags": [
      "futuristic",
      "energetic"
    ]
  },
  {
    "id": "v127",
    "title": "Noemotion Goldmask - Egypt Ejaculation (Sofa Sauce)",
    "description": "Watch Noemotion Goldmask - Egypt Ejaculation (Sofa Sauce) on YourSpace.",
    "content_type": "video",
    "file_url": "https://img.youtube.com/vi/yqjyJA5cjas/hqdefault.jpg",
    "view_count": 43323,
    "like_count": 973,
    "created_at": "2025-10-28T02:02:00.949Z",
    "vibe_tags": [
      "energetic",
      "futuristic"
    ]
  },
  {
    "id": "v128",
    "title": "(For REAL i Am)-sofa king sad boi",
    "description": "Watch (For REAL i Am)-sofa king sad boi on YourSpace.",
    "content_type": "video",
    "file_url": "https://img.youtube.com/vi/5uaNyE8Cyzk/hqdefault.jpg",
    "view_count": 18305,
    "like_count": 546,
    "created_at": "2025-12-20T12:10:17.471Z",
    "vibe_tags": [
      "energetic",
      "retro"
    ]
  },
  {
    "id": "v129",
    "title": "#aliceinwonderland #downtherabbithole #kaiberai #aivideoart #aimovie #trippyshorts #hallucination",
    "description": "Watch #aliceinwonderland #downtherabbithole #kaiberai #aivideoart #aimovie #trippyshorts #hallucination on YourSpace.",
    "content_type": "video",
    "file_url": "https://img.youtube.com/vi/Kh8eHXNG6G4/hqdefault.jpg",
    "view_count": 42933,
    "like_count": 180,
    "created_at": "2025-10-13T04:28:51.551Z",
    "vibe_tags": [
      "chill",
      "futuristic"
    ]
  },
  {
    "id": "v130",
    "title": "12matt3r The Sinister Power: NoEmotion GoldMask takes over #kaiberai #kaiber #ai",
    "description": "Watch 12matt3r The Sinister Power: NoEmotion GoldMask takes over #kaiberai #kaiber #ai on YourSpace.",
    "content_type": "video",
    "file_url": "https://img.youtube.com/vi/wt4NFp5PL3Y/hqdefault.jpg",
    "view_count": 45241,
    "like_count": 4311,
    "created_at": "2025-10-20T02:12:22.499Z",
    "vibe_tags": [
      "chill",
      "energetic"
    ]
  },
  {
    "id": "v131",
    "title": "bumpfest 2023 all filler no content 12matt3r submissions",
    "description": "Watch bumpfest 2023 all filler no content 12matt3r submissions on YourSpace.",
    "content_type": "video",
    "file_url": "https://img.youtube.com/vi/ufYws78_t1U/hqdefault.jpg",
    "view_count": 4054,
    "like_count": 4311,
    "created_at": "2025-12-06T16:22:04.832Z",
    "vibe_tags": [
      "chill",
      "energetic"
    ]
  },
  {
    "id": "v132",
    "title": "Slushwave Social Club compilation number 5",
    "description": "Watch Slushwave Social Club compilation number 5 on YourSpace.",
    "content_type": "video",
    "file_url": "https://img.youtube.com/vi/cMvRL4RQL00/hqdefault.jpg",
    "view_count": 12361,
    "like_count": 2548,
    "created_at": "2025-09-24T21:55:15.839Z",
    "vibe_tags": [
      "chill",
      "energetic"
    ]
  },
  {
    "id": "v133",
    "title": "The Text to Video Hidden Gems of kaiber Ai Weekly Jam 12matt3r",
    "description": "Watch The Text to Video Hidden Gems of kaiber Ai Weekly Jam 12matt3r on YourSpace.",
    "content_type": "video",
    "file_url": "https://img.youtube.com/vi/opMXFFFK0WY/hqdefault.jpg",
    "view_count": 45468,
    "like_count": 232,
    "created_at": "2025-12-19T10:33:41.809Z",
    "vibe_tags": [
      "chill",
      "energetic"
    ]
  },
  {
    "id": "v134",
    "title": "#Kaiberai Daily jam: Animal Kingdom 17/07/23",
    "description": "Watch #Kaiberai Daily jam: Animal Kingdom 17/07/23 on YourSpace.",
    "content_type": "video",
    "file_url": "https://img.youtube.com/vi/R-mmfYy2-5s/hqdefault.jpg",
    "view_count": 26078,
    "like_count": 4021,
    "created_at": "2025-11-04T20:59:00.299Z",
    "vibe_tags": [
      "retro",
      "energetic"
    ]
  },
  {
    "id": "v135",
    "title": "Noemotion Goldmask-Humble Pie | @largefatherbassmusic",
    "description": "Watch Noemotion Goldmask-Humble Pie | @largefatherbassmusic on YourSpace.",
    "content_type": "video",
    "file_url": "https://img.youtube.com/vi/yRwXeLeFVqg/hqdefault.jpg",
    "view_count": 15546,
    "like_count": 2309,
    "created_at": "2025-11-10T07:26:11.374Z",
    "vibe_tags": [
      "retro",
      "futuristic"
    ]
  },
  {
    "id": "v136",
    "title": "Noemotion Goldmask-Think Tank Diving (Sofa Sauce)",
    "description": "Watch Noemotion Goldmask-Think Tank Diving (Sofa Sauce) on YourSpace.",
    "content_type": "video",
    "file_url": "https://img.youtube.com/vi/dKR2nKsiRbs/hqdefault.jpg",
    "view_count": 47996,
    "like_count": 3909,
    "created_at": "2025-12-25T23:59:53.715Z",
    "vibe_tags": [
      "chill",
      "energetic"
    ]
  },
  {
    "id": "v137",
    "title": "Coming this it’s “that time again”",
    "description": "Watch Coming this it’s “that time again” on YourSpace.",
    "content_type": "video",
    "file_url": "https://img.youtube.com/vi/noRDcK1Sb3M/hqdefault.jpg",
    "view_count": 24106,
    "like_count": 211,
    "created_at": "2025-11-17T12:31:40.569Z",
    "vibe_tags": [
      "chill",
      "energetic"
    ]
  },
  {
    "id": "v138",
    "title": "Watch This Trippy Visualizer Without Any Music",
    "description": "Watch Watch This Trippy Visualizer Without Any Music on YourSpace.",
    "content_type": "video",
    "file_url": "https://img.youtube.com/vi/3ZFnAPVEtb4/hqdefault.jpg",
    "view_count": 22877,
    "like_count": 986,
    "created_at": "2026-01-09T01:42:29.354Z",
    "vibe_tags": [
      "retro",
      "chill"
    ]
  },
  {
    "id": "v139",
    "title": "Sofa Sessions: The Ultimate Goldmask Sunrize Collection",
    "description": "Watch Sofa Sessions: The Ultimate Goldmask Sunrize Collection on YourSpace.",
    "content_type": "video",
    "file_url": "https://img.youtube.com/vi/ea1QxnG-5cs/hqdefault.jpg",
    "view_count": 16649,
    "like_count": 2149,
    "created_at": "2025-11-29T14:43:27.524Z",
    "vibe_tags": [
      "futuristic",
      "retro"
    ]
  },
  {
    "id": "v140",
    "title": "Helter Skelter-AllTheFeelingsRegularFace :Godz Listening Party:",
    "description": "Watch Helter Skelter-AllTheFeelingsRegularFace :Godz Listening Party: on YourSpace.",
    "content_type": "video",
    "file_url": "https://img.youtube.com/vi/N8LkrMQeI2E/hqdefault.jpg",
    "view_count": 39166,
    "like_count": 998,
    "created_at": "2025-10-25T22:57:00.489Z",
    "vibe_tags": [
      "retro",
      "energetic"
    ]
  },
  {
    "id": "v141",
    "title": "godz listening party number 91 - J3rkanator for janitor",
    "description": "Watch godz listening party number 91 - J3rkanator for janitor on YourSpace.",
    "content_type": "video",
    "file_url": "https://img.youtube.com/vi/zZh_DyYoBhI/hqdefault.jpg",
    "view_count": 46144,
    "like_count": 4134,
    "created_at": "2025-11-21T14:44:34.972Z",
    "vibe_tags": [
      "energetic",
      "retro"
    ]
  },
  {
    "id": "v142",
    "title": "Trippy Bassnectar Visuals",
    "description": "Watch Trippy Bassnectar Visuals on YourSpace.",
    "content_type": "video",
    "file_url": "https://img.youtube.com/vi/y-hNdSKKl9Y/hqdefault.jpg",
    "view_count": 26043,
    "like_count": 933,
    "created_at": "2025-11-20T17:36:18.294Z",
    "vibe_tags": [
      "futuristic",
      "retro"
    ]
  },
  {
    "id": "v143",
    "title": "@GlitchGuildUnited weekly prompt “feedback”",
    "description": "Watch @GlitchGuildUnited weekly prompt “feedback” on YourSpace.",
    "content_type": "video",
    "file_url": "https://img.youtube.com/vi/Gcw4cPoAYu0/hqdefault.jpg",
    "view_count": 29910,
    "like_count": 4665,
    "created_at": "2025-10-23T18:22:33.624Z",
    "vibe_tags": [
      "energetic",
      "chill"
    ]
  },
  {
    "id": "v144",
    "title": "@GlitchGuildUnited weekly prompt “doorways”",
    "description": "Watch @GlitchGuildUnited weekly prompt “doorways” on YourSpace.",
    "content_type": "video",
    "file_url": "https://img.youtube.com/vi/xJYE3G8ohuI/hqdefault.jpg",
    "view_count": 38197,
    "like_count": 2965,
    "created_at": "2025-10-16T07:48:33.800Z",
    "vibe_tags": [
      "chill",
      "energetic"
    ]
  },
  {
    "id": "v145",
    "title": "@GlitchGuildUnited weekly Prompt ‘total Eclipse’",
    "description": "Watch @GlitchGuildUnited weekly Prompt ‘total Eclipse’ on YourSpace.",
    "content_type": "video",
    "file_url": "https://img.youtube.com/vi/GRaNsEjMHVM/hqdefault.jpg",
    "view_count": 21365,
    "like_count": 2870,
    "created_at": "2025-11-20T13:01:57.054Z",
    "vibe_tags": [
      "chill",
      "energetic"
    ]
  },
  {
    "id": "v146",
    "title": "@GlitchGuildUnited , weekly prompt ‘skating’",
    "description": "Watch @GlitchGuildUnited , weekly prompt ‘skating’ on YourSpace.",
    "content_type": "video",
    "file_url": "https://img.youtube.com/vi/ic3I0pKG_HA/hqdefault.jpg",
    "view_count": 39809,
    "like_count": 2009,
    "created_at": "2025-11-24T13:16:35.002Z",
    "vibe_tags": [
      "futuristic",
      "retro"
    ]
  },
  {
    "id": "v147",
    "title": "@GlitchGuildUnited weekly prompt “commercials”",
    "description": "Watch @GlitchGuildUnited weekly prompt “commercials” on YourSpace.",
    "content_type": "video",
    "file_url": "https://img.youtube.com/vi/vZBeHzQPkSw/hqdefault.jpg",
    "view_count": 38604,
    "like_count": 1419,
    "created_at": "2025-11-06T12:40:36.143Z",
    "vibe_tags": [
      "retro",
      "energetic"
    ]
  },
  {
    "id": "v148",
    "title": "Mac Miller Reimagined: A Soulful Remix Tribute Mixtape",
    "description": "Watch Mac Miller Reimagined: A Soulful Remix Tribute Mixtape on YourSpace.",
    "content_type": "video",
    "file_url": "https://img.youtube.com/vi/tUZlDjZ3YhM/hqdefault.jpg",
    "view_count": 25095,
    "like_count": 5065,
    "created_at": "2025-12-02T10:01:29.058Z",
    "vibe_tags": [
      "energetic",
      "chill"
    ]
  }
]
